discord_flask/__init__.py
discord_flask/_http.py
discord_flask/client.py
discord_flask/configs.py
discord_flask/embed.py
discord_flask/emoji.py
discord_flask/exceptions.py
discord_flask/message.py
discord_flask/role.py
discord_flask/utils.py
discord_flask/models/__init__.py
discord_flask/models/base.py
discord_flask/models/channel.py
discord_flask/models/connections.py
discord_flask/models/guild.py
discord_flask/models/integration.py
discord_flask/models/member.py
discord_flask/models/role.py
discord_flask/models/user.py
discord_flask/types/__init__.py
discord_flask/types/embed.py
discord_flask/types/emoji.py
discord_flask/types/permissions.py
discord_flask/types/role.py
Discord_Flask-1.0.4.dist-info/LICENSE
Discord_Flask-1.0.4.dist-info/METADATA
Discord_Flask-1.0.4.dist-info/WHEEL
Discord_Flask-1.0.4.dist-info/top_level.txt
Discord_Flask-1.0.4.dist-info/RECORD
